py_codesave/__init__.py
py_codesave/main.py
py_codesave-0.0.3.dist-info/METADATA
py_codesave-0.0.3.dist-info/WHEEL
py_codesave-0.0.3.dist-info/top_level.txt
py_codesave-0.0.3.dist-info/RECORD
