Metadata-Version: 2.1
Name: py-codesave
Version: 0.0.3
Summary: Save the code automatically.
Home-page: https://github.com/sawol/py_codesave/
Author: sawol
Author-email: sawol634@gmail.com
License: UNKNOWN
Platform: UNKNOWN
Classifier: Programming Language :: Python :: 3
Classifier: Programming Language :: Python :: 3.2
Classifier: Programming Language :: Python :: 3.3
Classifier: Programming Language :: Python :: 3.4
Classifier: Programming Language :: Python :: 3.5
Classifier: Programming Language :: Python :: 3.6
Classifier: Programming Language :: Python :: 3.7
Requires-Python: >=3
Requires-Dist: beautifulsoup4
Requires-Dist: requests
Requires-Dist: lxml
Requires-Dist: selenium
Requires-Dist: pygithub
